zope.sqlalchemy-3.0-py3.11-nspkg.pth
zope/sqlalchemy/README.rst
zope/sqlalchemy/__init__.py
zope/sqlalchemy/datamanager.py
zope/sqlalchemy/tests.py
zope.sqlalchemy-3.0.dist-info/LICENSE.txt
zope.sqlalchemy-3.0.dist-info/METADATA
zope.sqlalchemy-3.0.dist-info/WHEEL
zope.sqlalchemy-3.0.dist-info/namespace_packages.txt
zope.sqlalchemy-3.0.dist-info/top_level.txt
zope.sqlalchemy-3.0.dist-info/RECORD
