Metadata-Version: 2.1
Name: zope.sqlalchemy
Version: 3.0
Summary: Minimal Zope/SQLAlchemy transaction integration
Home-page: https://github.com/zopefoundation/zope.sqlalchemy
Author: Laurence Rowe
Author-email: laurence@lrowe.co.uk
License: ZPL 2.1
Keywords: zope zope3 sqlalchemy
Classifier: Development Status :: 5 - Production/Stable
Classifier: Framework :: Pyramid
Classifier: Framework :: Zope :: 3
Classifier: Framework :: Zope :: 5
Classifier: Intended Audience :: Developers
Classifier: License :: OSI Approved :: Zope Public License
Classifier: Programming Language :: Python
Classifier: Programming Language :: Python :: 3
Classifier: Programming Language :: Python :: 3.7
Classifier: Programming Language :: Python :: 3.8
Classifier: Programming Language :: Python :: 3.9
Classifier: Programming Language :: Python :: 3.10
Classifier: Programming Language :: Python :: 3.11
Classifier: Programming Language :: Python :: Implementation :: CPython
Classifier: Topic :: Database
Classifier: Topic :: Software Development :: Libraries :: Python Modules
Requires-Python: >=3.7
License-File: LICENSE.txt
Requires-Dist: packaging
Requires-Dist: setuptools
Requires-Dist: SQLAlchemy (!=1.4.0,!=1.4.1,!=1.4.2,!=1.4.3,!=1.4.4,!=1.4.5,!=1.4.6,>=1.1)
Requires-Dist: transaction (>=1.6.0)
Requires-Dist: zope.interface (>=3.6.0)
Provides-Extra: test
Requires-Dist: zope.testing ; extra == 'test'
